salamenc/__init__.py
salamenc/salamenc.py
salamenc-1.3.dist-info/LICENSE
salamenc-1.3.dist-info/METADATA
salamenc-1.3.dist-info/WHEEL
salamenc-1.3.dist-info/top_level.txt
salamenc-1.3.dist-info/RECORD
