Metadata-Version: 2.1
Name: salamenc
Version: 1.3
Summary: For developers Encrypt tools
Home-page: https://t.me/T5B55
Author: salammzere3
Author-email: salamhunter@gmail.com
Project-URL: Bug Tracker, https://github.com/pypa/sampleproject/issues
Keywords: salamenc
Classifier: Development Status :: 1 - Planning
Classifier: Intended Audience :: Developers
Classifier: Programming Language :: Python :: 3
Classifier: Operating System :: Unix
Classifier: Operating System :: MacOS :: MacOS X
Classifier: Operating System :: Microsoft :: Windows
License-File: LICENSE
